Metadata-Version: 2.1
Name: aochagavia_example_lib
Version: 0.1.2
Summary: A minimal example Python library
Author: Adolfo Ochagavía
Author-email: test@example.com
Classifier: Programming Language :: Python :: 3
Classifier: License :: OSI Approved :: MIT License
Classifier: Operating System :: OS Independent
